Workbook

Sheet Premissas
A1: Premissa (edite as células azuis) | B1: Valor | C1: Fonte / observação
A2: Estabelecimentos agropecuários no Paraná | B2: 305154 | C2: IBGE, Censo Agropecuário 2017
A3: % pequenos produtores (agricultura familiar) | B3: 0.75 | C3: Informado: 75% (IDR-Paraná / IBGE 2017)
A4: Pequenos produtores no Paraná | B4: =B2*B3 -> 228865.5 | C4: Calculado
A5: Meta ano 1 (% dos pequenos) | B5: 0.05 | C5: Informado: 5%
A6: Meta de produtores no fim do ano 1 | B6: 11450 | C6: Informado: 11.450 (5% de 228.866 = 11.443)
A7: Mensalidade média por produtor (R$) | B7: 150 | C7: Informado: faixa R$ 150–400; base conservadora no piso
A8: Salário mínimo 2026 (R$) | B8: 1621 | C8: Decreto: R$ 1.621 desde 01/01/2026
A9: Piso do agrônomo, 8 h/dia (R$) | B9: =8.5*B8 -> 13778.5 | C9: Lei 4.950-A/66: 8,5 salários mínimos
A10: Fator de encargos CLT | B10: 1.7 | C10: Estimativa; confirmar com o contador
A11: Agrônomos fixos a campo | B11: 2 | C11: Informado: 2
A12: Programação, 1 pessoa (R$/mês, PJ) | B12: 10000 | C12: Informado: 1 pessoa; valor estimado
A13: Marketing, 1 pessoa (R$/mês, PJ) | B13: 6000 | C13: Informado: 1 pessoa; valor estimado
A14: Administrativo, contador, CREA/ART (R$/mês) | B14: 3000 | C14: Estimativa
A15: Ferramentas e softwares (R$/mês) | B15: 1000 | C15: Estimativa
A16: Servidores + IA + WhatsApp por produtor ativo (R$/mês) | B16: 5 | C16: Estimativa
A17: % de produtores que sobem para o agrônomo por mês | B17: 0.1 | C17: Estimativa: a IA resolve a rotina
A18: Pagamento ao agrônomo parceiro por caso/receituário (R$) | B18: 40 | C18: Informado: por caso e receituário, sem vínculo; valor estimado
A19: Taxa de meios de pagamento (% da receita) | B19: 0.035 | C19: Estimativa
A20: Impostos sobre a receita | B20: 0.15 | C20: Estimativa Lucro Presumido + ISS; confirmar com o contador
A21: Custo de aquisição por novo produtor - CAC (R$) | B21: 60 | C21: Estimativa: cooperativas, sindicatos, eventos
... A23: Agricultores familiares no Brasil | B23: 3897408 | C23: IBGE, Censo Agropecuário 2017

Sheet Mensal ano 1
A1: Mês | B1: Novos | C1: Ativos | D1: Receita | E1: Impostos | F1: Taxas pgto | G1: Infra+IA | H1: Agrônomo por caso | I1: Aquisição (CAC) | J1: Equipe fixa | K1: Adm+ferram. | L1: Custo total | M1: Lucro | N1: Lucro acumulado
A2: 1 | B2: =Premissas!$B$6/12 -> 954.16667 | C2: =0*(1-Premissas!$B$22)+B2 -> 954.16667 | D2: =C2*Premissas!$B$7 -> 143125 | E2: =D2*Premissas!$B$20 -> 21468.75 | F2: =D2*Premissas!$B$19 -> 5009.375 | G2: =C2*Premissas!$B$16 -> 4770.8333 | H2: =C2*Premissas!$B$17*Premissas!$B$18 -> 3816.6667 | I2: =B2*Premissas!$B$21 -> 57250 | J2: =Premissas!$B$12+Premissas!$B$13+Premissas!$B$11*Premissas!$B$9*Premissas!$B$10 -> 62846.9 | K2: =Premissas!$B$14+Premissas!$B$15 -> 4000 | L2: =SUM(E2:K2) -> 159162.52 | M2: =D2-L2 -> -16037.525 | N2: =M2 -> -16037.525
A3: 2 | B3: =Premissas!$B$6/12 -> 954.16667 | C3: =C2*(1-Premissas!$B$22)+B3 -> 1889.25 | D3: =C3*Premissas!$B$7 -> 283387.5 | E3: =D3*Premissas!$B$20 -> 42508.125 | F3: =D3*Premissas!$B$19 -> 9918.5625 | G3: =C3*Premissas!$B$16 -> 9446.25 | H3: =C3*Premissas!$B$17*Premissas!$B$18 -> 7557 | I3: =B3*Premissas!$B$21 -> 57250 | J3: =Premissas!$B$12+Premissas!$B$13+Premissas!$B$11*Premissas!$B$9*Premissas!$B$10 -> 62846.9 | K3: =Premissas!$B$14+Premissas!$B$15 -> 4000 | L3: =SUM(E3:K3) -> 193526.84 | M3: =D3-L3 -> 89860.663 | N3: =N2+M3 -> 73823.138
A4: 3 | B4: =Premissas!$B$6/12 -> 954.16667 | C4: =C3*(1-Premissas!$B$22)+B4 -> 2805.6317 | D4: =C4*Premissas!$B$7 -> 420844.75 | E4: =D4*Premissas!$B$20 -> 63126.712 | F4: =D4*Premissas!$B$19 -> 14729.566 | G4: =C4*Premissas!$B$16 -> 14028.158 | H4: =C4*Premissas!$B$17*Premissas!$B$18 -> 11222.527 | I4: =B4*Premissas!$B$21 -> 57250 | J4: =Premissas!$B$12+Premissas!$B$13+Premissas!$B$11*Premissas!$B$9*Premissas!$B$10 -> 62846.9 | K4: =Premissas!$B$14+Premissas!$B$15 -> 4000 | L4: =SUM(E4:K4) -> 227203.86 | M4: =D4-L4 -> 193640.89 | N4: =N3+M4 -> 267464.02
A5: 4 | B5: =Premissas!$B$6/12 -> 954.16667 | C5: =C4*(1-Premissas!$B$22)+B5 -> 3703.6857 | D5: =C5*Premissas!$B$7 -> 555552.85 | E5: =D5*Premissas!$B$20 -> 83332.928 | F5: =D5*Premissas!$B$19 -> 19444.35 | G5: =C5*Premissas!$B$16 -> 18518.429 | H5: =C5*Premissas!$B$17*Premissas!$B$18 -> 14814.743 | I5: =B5*Premissas!$B$21 -> 57250 | J5: =Premissas!$B$12+Premissas!$B$13+Premissas!$B$11*Premissas!$B$9*Premissas!$B$10 -> 62846.9 | K5: =Premissas!$B$14+Premissas!$B$15 -> 4000 | L5: =SUM(E5:K5) -> 260207.35 | M5: =D5-L5 -> 295345.51 | N5: =N4+M5 -> 562809.53
A6: 5 | B6: =Premissas!$B$6/12 -> 954.16667 | C6: =C5*(1-Premissas!$B$22)+B6 -> 4583.7787 | D6: =C6*Premissas!$B$7 -> 687566.8 | E6: =D6*Premissas!$B$20 -> 103135.02 | F6: =D6*Premissas!$B$19 -> 24064.838 | G6: =C6*Premissas!$B$16 -> 22918.893 | H6: =C6*Premissas!$B$17*Premissas!$B$18 -> 18335.115 | I6: =B6*Premissas!$B$21 -> 57250 | J6: =Premissas!$B$12+Premissas!$B$13+Premissas!$B$11*Premissas!$B$9*Premissas!$B$10 -> 62846.9 | K6: =Premissas!$B$14+Premissas!$B$15 -> 4000 | L6: =SUM(E6:K6) -> 292550.77 | M6: =D6-L6 -> 395016.03 | N6: =N5+M6 -> 957825.56
A7: 6 | B7: =Premissas!$B$6/12 -> 954.16667 | C7: =C6*(1-Premissas!$B$22)+B7 -> 5446.2697 | D7: =C7*Premissas!$B$7 -> 816940.46 | E7: =D7*Premissas!$B$20 -> 122541.07 | F7: =D7*Premissas!$B$19 -> 28592.916 | G7: =C7*Premissas!$B$16 -> 27231.349 | H7: =C7*Premissas!$B$17*Premissas!$B$18 -> 21785.079 | I7: =B7*Premissas!$B$21 -> 57250 | J7: =Premissas!$B$12+Premissas!$B$13+Premissas!$B$11*Premissas!$B$9*Premissas!$B$10 -> 62846.9 | K7: =Premissas!$B$14+Premissas!$B$15 -> 4000 | L7: =SUM(E7:K7) -> 324247.31 | M7: =D7-L7 -> 492693.15 | N7: =N6+M7 -> 1450518.7
A8: 7 | B8: =Premissas!$B$6/12 -> 954.16667 | C8: =C7*(1-Premissas!$B$22)+B8 -> 6291.511 | D8: =C8*Premissas!$B$7 -> 943726.65 | E8: =D8*Premissas!$B$20 -> 141559 | F8: =D8*Premissas!$B$19 -> 33030.433 | G8: =C8*Premissas!$B$16 -> 31457.555 | H8: =C8*Premissas!$B$17*Premissas!$B$18 -> 25166.044 | I8: =B8*Premissas!$B$21 -> 57250 | J8: =Premissas!$B$12+Premissas!$B$13+Premissas!$B$11*Premissas!$B$9*Premissas!$B$10 -> 62846.9 | K8: =Premissas!$B$14+Premissas!$B$15 -> 4000 | L8: =SUM(E8:K8) -> 355309.93 | M8: =D8-L8 -> 588416.72 | N8: =N7+M8 -> 2038935.4
A9: 8 | B9: =Premissas!$B$6/12 -> 954.16667 | C9: =C8*(1-Premissas!$B$22)+B9 -> 7119.8475 | D9: =C9*Premissas!$B$7 -> 1067977.1 | E9: =D9*Premissas!$B$20 -> 160196.57 | F9: =D9*Premissas!$B$19 -> 37379.199 | G9: =C9*Premissas!$B$16 -> 35599.237 | H9: =C9*Premissas!$B$17*Premissas!$B$18 -> 28479.39 | I9: =B9*Premissas!$B$21 -> 57250 | J9: =Premissas!$B$12+Premissas!$B$13+Premissas!$B$11*Premissas!$B$9*Premissas!$B$10 -> 62846.9 | K9: =Premissas!$B$14+Premissas!$B$15 -> 4000 | L9: =SUM(E9:K9) -> 385751.29 | M9: =D9-L9 -> 682225.83 | N9: =N8+M9 -> 2721161.3
A10: 9 | B10: =Premissas!$B$6/12 -> 954.16667 | C10: =C9*(1-Premissas!$B$22)+B10 -> 7931.6172 | D10: =C10*Premissas!$B$7 -> 1189742.6 | E10: =D10*Premissas!$B$20 -> 178461.39 | F10: =D10*Premissas!$B$19 -> 41640.99 | G10: =C10*Premissas!$B$16 -> 39658.086 | H10: =C10*Premissas!$B$17*Premissas!$B$18 -> 31726.469 | I10: =B10*Premissas!$B$21 -> 57250 | J10: =Premissas!$B$12+Premissas!$B$13+Premissas!$B$11*Premissas!$B$9*Premissas!$B$10 -> 62846.9 | K10: =Premissas!$B$14+Premissas!$B$15 -> 4000 | L10: =SUM(E10:K10) -> 415583.83 | M10: =D10-L10 -> 774158.75 | N10: =N9+M10 -> 3495320
A11: 10 | B11: =Premissas!$B$6/12 -> 954.16667 | C11: =C10*(1-Premissas!$B$22)+B11 -> 8727.1515 | D11: =C11*Premissas!$B$7 -> 1309072.7 | E11: =D11*Premissas!$B$20 -> 196360.91 | F11: =D11*Premissas!$B$19 -> 45817.545 | G11: =C11*Premissas!$B$16 -> 43635.758 | H11: =C11*Premissas!$B$17*Premissas!$B$18 -> 34908.606 | I11: =B11*Premissas!$B$21 -> 57250 | J11: =Premissas!$B$12+Premissas!$B$13+Premissas!$B$11*Premissas!$B$9*Premissas!$B$10 -> 62846.9 | K11: =Premissas!$B$14+Premissas!$B$15 -> 4000 | L11: =SUM(E11:K11) -> 444819.72 | M11: =D11-L11 -> 864253.01 | N11: =N10+M11 -> 4359573
A12: 11 | B12: =Premissas!$B$6/12 -> 954.16667 | C12: =C11*(1-Premissas!$B$22)+B12 -> 9506.7751 | D12: =C12*Premissas!$B$7 -> 1426016.3 | E12: =D12*Premissas!$B$20 -> 213902.44 | F12: =D12*Premissas!$B$19 -> 49910.569 | G12: =C12*Premissas!$B$16 -> 47533.876 | H12: =C12*Premissas!$B$17*Premissas!$B$18 -> 38027.101 | I12: =B12*Premissas!$B$21 -> 57250 | J12: =Premissas!$B$12+Premissas!$B$13+Premissas!$B$11*Premissas!$B$9*Premissas!$B$10 -> 62846.9 | K12: =Premissas!$B$14+Premissas!$B$15 -> 4000 | L12: =SUM(E12:K12) -> 473470.89 | M12: =D12-L12 -> 952545.38 | N12: =N11+M12 -> 5312118.4
A13: 12 | B13: =Premissas!$B$6/12 -> 954.16667 | C13: =C12*(1-Premissas!$B$22)+B13 -> 10270.806 | D13: =C13*Premissas!$B$7 -> 1540620.9 | E13: =D13*Premissas!$B$20 -> 231093.14 | F13: =D13*Premissas!$B$19 -> 53921.733 | G13: =C13*Premissas!$B$16 -> 51354.032 | H13: =C13*Premissas!$B$17*Premissas!$B$18 -> 41083.225 | I13: =B13*Premissas!$B$21 -> 57250 | J13: =Premissas!$B$12+Premissas!$B$13+Premissas!$B$11*Premissas!$B$9*Premissas!$B$10 -> 62846.9 | K13: =Premissas!$B$14+Premissas!$B$15 -> 4000 | L13: =SUM(E13:K13) -> 501549.03 | M13: =D13-L13 -> 1039071.9 | N13: =N12+M13 -> 6351190.3
A14: Ano 1 | D14: =SUM(D2:D13) -> 10384574 | E14: =SUM(E2:E13) -> 1557686 | F14: =SUM(F2:F13) -> 363460.08 | G14: =SUM(G2:G13) -> 346152.46 | H14: =SUM(H2:H13) -> 276921.96 | I14: =SUM(I2:I13) -> 687000 | J14: =SUM(J2:J13) -> 754162.8 | K14: =SUM(K2:K13) -> 48000 | ... M14: =SUM(M2:M13) -> 6351190.3

Sheet Resumo
A1: Indicador | B1: Valor
A2: Receita ano 1 | B2: ='Mensal ano 1'!D14 -> 10384574
A3: Custo total ano 1 | B3: ='Mensal ano 1'!L14 -> 4033383.3
A4: Lucro ano 1 | B4: ='Mensal ano 1'!M14 -> 6351190.3
A5: Margem ano 1 | B5: =B4/B2 -> 0.61159856
A6: Margem de contribuição por produtor/mês | B6: =Premissas!B7*(1-Premissas!B20-Premissas!B19)-Premissas!B16-Premissas!B17*Premissas!B18 -> 113.25
A7: Custo fixo mensal | B7: ='Mensal ano 1'!J2+'Mensal ano 1'!K2 -> 66846.9
A8: Ponto de equilíbrio (produtores ativos) | B8: =ROUNDUP(B7/B6,0) -> 591
A9: Mercado Paraná (pequenos × mensalidade × 12) | B9: =Premissas!B4*Premissas!B7*12 -> 411957900
A10: Mercado Brasil (agric. familiar × mensalidade × 12) | B10: =Premissas!B23*Premissas!B7*12 -> 7015334400
